multidb_mcp/__init__.py
multidb_mcp/__main__.py
multidb_mcp/database_manager.py
multidb_mcp/log.py
multidb_mcp/server.py
multidb_mcp-0.3.0.dist-info/METADATA
multidb_mcp-0.3.0.dist-info/WHEEL
multidb_mcp-0.3.0.dist-info/entry_points.txt
multidb_mcp-0.3.0.dist-info/licenses/LICENSE
multidb_mcp-0.3.0.dist-info/RECORD
