Metadata-Version: 2.4
Name: multidb-mcp
Version: 0.3.0
Summary: A multi-database MCP server supporting multiple remote databases
Author-email: Nick <nick@example.com>
License-File: LICENSE
Requires-Python: >=3.10
Requires-Dist: fastmcp>=0.2.0
Requires-Dist: psycopg2-binary>=2.9.0
Requires-Dist: pydantic>=2.0.0
Requires-Dist: pymysql>=1.1.0
Requires-Dist: pytest>=9.0.2
Requires-Dist: sqlalchemy>=2.0.0
Requires-Dist: typer>=0.9.0
